{
  "credit" : "Made with Blockbench",
  "elements" : [ {
    "faces" : {
      "down" : {
        "texture" : "#20",
        "uv" : [ 16, 0, 0, 16 ]
      },
      "east" : {
        "texture" : "#19",
        "uv" : [ 0, 0, 16, 16 ]
      },
      "north" : {
        "texture" : "#19",
        "uv" : [ 0, 0, 16, 16 ]
      },
      "south" : {
        "texture" : "#19",
        "uv" : [ 0, 0, 16, 16 ]
      },
      "up" : {
        "texture" : "#20",
        "uv" : [ 16, 16, 0, 0 ]
      },
      "west" : {
        "texture" : "#19",
        "uv" : [ 0, 0, 16, 16 ]
      }
    },
    "from" : [ 0, 0, 0 ],
    "to" : [ 16, 16, 16 ]
  } ],
  "format_version" : "1.9.0",
  "textures" : {
    "19" : "tts:block/sov/sov_interior_beige_panel_split",
    "20" : "tts:block/sov/sov_interior_beige_panel",
    "particle" : "tts:block/sov/sov_outer_corridor_top_2"
  }
}